chainlink_feeds/__init__.py
chainlink_feeds/chainlink_feeds.py
test/__init__.py
test/test_chainlink_feeds.py
test/test_chainlink_feeds_with_rpc_url.py
chainlink_feeds-0.2.9.dist-info/LICENSE
chainlink_feeds-0.2.9.dist-info/METADATA
chainlink_feeds-0.2.9.dist-info/WHEEL
chainlink_feeds-0.2.9.dist-info/top_level.txt
chainlink_feeds-0.2.9.dist-info/RECORD
